LICENSE
README.md
pyproject.toml
tartempion.py
tartempion.egg-info/PKG-INFO
tartempion.egg-info/SOURCES.txt
tartempion.egg-info/dependency_links.txt
tartempion.egg-info/top_level.txt