Metadata-Version: 2.1
Name: tartempion
Version: 0.0.2
Author-email: Julien Castiaux <julien.castiaux@gmail.com>
License-File: LICENSE
